radicale_auth_PAM/__init__.py
radicale_auth_PAM-0.2.dist-info/DESCRIPTION.rst
radicale_auth_PAM-0.2.dist-info/METADATA
radicale_auth_PAM-0.2.dist-info/RECORD
radicale_auth_PAM-0.2.dist-info/WHEEL
radicale_auth_PAM-0.2.dist-info/metadata.json
radicale_auth_PAM-0.2.dist-info/top_level.txt
