Metadata-Version: 2.0
Name: radicale-auth-PAM
Version: 0.2
Summary: PAM authentication plugin for Radicale
Home-page: https://gitlab.com/jello/radicale_auth_PAM
Author: Joseph Nahmias
Author-email: joe@nahmias.net
License: GPL3+
Platform: UNKNOWN
Classifier: Development Status :: 4 - Beta
Classifier: Environment :: Plugins 
Classifier: Intended Audience :: System Administrators
Classifier: License :: OSI Approved :: GNU General Public License v3 or later (GPLv3+)
Classifier: Operating System :: POSIX :: Linux
Classifier: Programming Language :: Python :: 3
Classifier: Topic :: Security
Classifier: Topic :: System :: Systems Administration :: Authentication/Directory
Requires-Dist: python-pam
